{
  "main": {
    "id": "b8ab2a2f9e87527e",
    "type": "split",
    "children": [
      {
        "id": "547edfd78d4b070a",
        "type": "tabs",
        "children": [
          {
            "id": "3fc5eaeedc94d23f",
            "type": "leaf",
            "state": {
              "type": "markdown",
              "state": {
                "file": "posts/202404151715.md",
                "mode": "source",
                "backlinks": false,
                "source": false
              }
            }
          }
        ]
      }
    ],
    "direction": "vertical"
  },
  "left": {
    "id": "14b500477f37bb50",
    "type": "split",
    "children": [
      {
        "id": "db64806cc7b1cf45",
        "type": "tabs",
        "children": [
          {
            "id": "055dc62e2c5d1a78",
            "type": "leaf",
            "state": {
              "type": "file-explorer",
              "state": {
                "sortOrder": "alphabetical"
              }
            }
          },
          {
            "id": "4d51d14493de27ff",
            "type": "leaf",
            "state": {
              "type": "search",
              "state": {
                "query": "",
                "matchingCase": false,
                "explainSearch": false,
                "collapseAll": false,
                "extraContext": false,
                "sortOrder": "alphabetical"
              }
            }
          },
          {
            "id": "a1cab342c058053b",
            "type": "leaf",
            "state": {
              "type": "bookmarks",
              "state": {}
            }
          }
        ]
      }
    ],
    "direction": "horizontal",
    "width": 300
  },
  "right": {
    "id": "997ff41a24ddfb5d",
    "type": "split",
    "children": [
      {
        "id": "48cf569ba0509f0d",
        "type": "tabs",
        "children": [
          {
            "id": "21ae490fe3183170",
            "type": "leaf",
            "state": {
              "type": "backlink",
              "state": {
                "file": "posts/202404151715.md",
                "collapseAll": false,
                "extraContext": false,
                "sortOrder": "alphabetical",
                "showSearch": false,
                "searchQuery": "",
                "backlinkCollapsed": false,
                "unlinkedCollapsed": true
              }
            }
          },
          {
            "id": "2f890f4031b84ffb",
            "type": "leaf",
            "state": {
              "type": "outgoing-link",
              "state": {
                "file": "posts/202404151715.md",
                "linksCollapsed": false,
                "unlinkedCollapsed": true
              }
            }
          },
          {
            "id": "a58af95cf9d26c3f",
            "type": "leaf",
            "state": {
              "type": "tag",
              "state": {
                "sortOrder": "frequency",
                "useHierarchy": true
              }
            }
          },
          {
            "id": "3f2a6cf2408e6a84",
            "type": "leaf",
            "state": {
              "type": "outline",
              "state": {
                "file": "posts/202404151715.md"
              }
            }
          }
        ]
      }
    ],
    "direction": "horizontal",
    "width": 300,
    "collapsed": true
  },
  "left-ribbon": {
    "hiddenItems": {
      "switcher:Open quick switcher": false,
      "graph:Open graph view": false,
      "canvas:Create new canvas": false,
      "daily-notes:Open today's daily note": false,
      "command-palette:Open command palette": false,
      "zk-prefixer:Create new unique note": false,
      "templater-obsidian:Templater": false,
      "kr-book-info-plugin:Add Book Info": false
    }
  },
  "active": "3fc5eaeedc94d23f",
  "lastOpenFiles": [
    "posts/202404151715.md",
    "posts/202312271313.md",
    "posts/202401291636.md",
    "books/엔터프라이즈 플러터 핸드북.md",
    "posts/202404092355.md",
    "posts/202401071414.md",
    "posts/202404151521.md",
    "assets/Pasted image 20231220144643.png",
    "books/디지털 트랜스포메이션 엔진.md",
    "books/더 시스템 THE SYSTEM.md",
    "books/모두의 네트워크.md",
    "posts/202402021525.md",
    "posts/202402112036.md",
    "posts/202404141129.md",
    "posts/202404141130.md",
    "templates/Post template.md",
    "posts/202312301624.md",
    "books/1초의 탄생.md",
    "assets/university_business_receipt_screenshot.png",
    "books/내가 원하는 곳에 나를 데려가라.md",
    "books/혁신기업의 딜레마.md",
    "books/코딩도 하고 사장도 합니다.md",
    "books/진화된 마케팅 그로스 해킹.md",
    "books/이펙티브 엔지니어.md",
    "books/설득의 심리학 4부작 세트.md",
    "books/마케팅 설계자.md",
    "books/논리적 사고를 기르는 알고리즘.md",
    "books/THE GOAL 더 골 2.md",
    "assets/inu_business_edu.png",
    "assets/MailAttachment.jpeg",
    "templates",
    "template"
  ]
}